refinire_rag_docling/__init__.py
refinire_rag_docling/loader.py
refinire_rag_docling/models.py
refinire_rag_docling/services.py
refinire_rag_docling-0.0.1.dist-info/METADATA
refinire_rag_docling-0.0.1.dist-info/WHEEL
refinire_rag_docling-0.0.1.dist-info/licenses/LICENSE
refinire_rag_docling-0.0.1.dist-info/RECORD
