Metadata-Version: 2.4
Name: refinire-rag-docling
Version: 0.0.1
Summary: Docling plugin for refinire-rag to read various document formats
License-File: LICENSE
Requires-Python: >=3.10
Requires-Dist: docling>=1.0.0
Provides-Extra: dev
Requires-Dist: pytest-cov>=4.1.0; extra == 'dev'
Requires-Dist: pytest>=8.0.0; extra == 'dev'
